{
  "opencollection": "1.0.0",
  "info": {
    "name": "BigPanda API",
    "version": "v2"
  },
  "items": [
    {
      "info": {
        "name": "Alerts",
        "type": "folder"
      },
      "items": [
        {
          "info": {
            "name": "BigPanda Send Alert",
            "type": "http"
          },
          "http": {
            "method": "POST",
            "url": "https://api.bigpanda.io/data/v2/alerts",
            "body": {
              "type": "json",
              "data": "{}"
            },
            "auth": {
              "type": "bearer",
              "token": "{{bearerToken}}"
            }
          },
          "docs": "Ingests a monitoring alert into BigPanda for correlation and incident management."
        }
      ]
    },
    {
      "info": {
        "name": "Environments",
        "type": "folder"
      },
      "items": [
        {
          "info": {
            "name": "BigPanda List Environments",
            "type": "http"
          },
          "http": {
            "method": "GET",
            "url": "https://api.bigpanda.io/resources/v2.0/environments",
            "auth": {
              "type": "bearer",
              "token": "{{bearerToken}}"
            }
          },
          "docs": "Returns a list of all BigPanda environments."
        },
        {
          "info": {
            "name": "BigPanda Create Environment",
            "type": "http"
          },
          "http": {
            "method": "POST",
            "url": "https://api.bigpanda.io/resources/v2.0/environments",
            "body": {
              "type": "json",
              "data": "{}"
            },
            "auth": {
              "type": "bearer",
              "token": "{{bearerToken}}"
            }
          },
          "docs": "Creates a new incident grouping environment."
        },
        {
          "info": {
            "name": "BigPanda Get Environment",
            "type": "http"
          },
          "http": {
            "method": "GET",
            "url": "https://api.bigpanda.io/resources/v2.0/environments/:id",
            "params": [
              {
                "name": "id",
                "value": "env-abc123",
                "type": "path"
              }
            ],
            "auth": {
              "type": "bearer",
              "token": "{{bearerToken}}"
            }
          },
          "docs": "Returns a single environment by ID."
        },
        {
          "info": {
            "name": "BigPanda Delete Environment",
            "type": "http"
          },
          "http": {
            "method": "DELETE",
            "url": "https://api.bigpanda.io/resources/v2.0/environments/:id",
            "params": [
              {
                "name": "id",
                "value": "env-abc123",
                "type": "path"
              }
            ],
            "auth": {
              "type": "bearer",
              "token": "{{bearerToken}}"
            }
          },
          "docs": "Deletes an environment by ID."
        }
      ]
    },
    {
      "info": {
        "name": "Incidents",
        "type": "folder"
      },
      "items": [
        {
          "info": {
            "name": "BigPanda List Incidents",
            "type": "http"
          },
          "http": {
            "method": "GET",
            "url": "https://api.bigpanda.io/resources/v2.0/environments/:environment_id/incidents",
            "params": [
              {
                "name": "environment_id",
                "value": "env-abc123",
                "type": "path"
              },
              {
                "name": "active",
                "value": "",
                "type": "query",
                "description": "Filter by active incidents."
              }
            ],
            "auth": {
              "type": "bearer",
              "token": "{{bearerToken}}"
            }
          },
          "docs": "Returns a list of incidents for the specified environment."
        },
        {
          "info": {
            "name": "BigPanda Get Incident",
            "type": "http"
          },
          "http": {
            "method": "GET",
            "url": "https://api.bigpanda.io/resources/v2.0/environments/:environment_id/incidents/:incident_id",
            "params": [
              {
                "name": "environment_id",
                "value": "env-abc123",
                "type": "path"
              },
              {
                "name": "incident_id",
                "value": "inc-abc123",
                "type": "path"
              }
            ],
            "auth": {
              "type": "bearer",
              "token": "{{bearerToken}}"
            }
          },
          "docs": "Returns details for a single incident."
        }
      ]
    },
    {
      "info": {
        "name": "Maintenance Plans",
        "type": "folder"
      },
      "items": [
        {
          "info": {
            "name": "BigPanda List Maintenance Plans",
            "type": "http"
          },
          "http": {
            "method": "GET",
            "url": "https://api.bigpanda.io/resources/v2.0/maintenance-plans",
            "auth": {
              "type": "bearer",
              "token": "{{bearerToken}}"
            }
          },
          "docs": "Returns all maintenance plans."
        },
        {
          "info": {
            "name": "BigPanda Create Maintenance Plan",
            "type": "http"
          },
          "http": {
            "method": "POST",
            "url": "https://api.bigpanda.io/resources/v2.0/maintenance-plans",
            "body": {
              "type": "json",
              "data": "{}"
            },
            "auth": {
              "type": "bearer",
              "token": "{{bearerToken}}"
            }
          },
          "docs": "Creates a new maintenance plan to suppress alerts during a window."
        }
      ]
    },
    {
      "info": {
        "name": "Changes",
        "type": "folder"
      },
      "items": [
        {
          "info": {
            "name": "BigPanda Send Change",
            "type": "http"
          },
          "http": {
            "method": "POST",
            "url": "https://api.bigpanda.io/data/changes",
            "body": {
              "type": "json",
              "data": "{}"
            },
            "auth": {
              "type": "bearer",
              "token": "{{bearerToken}}"
            }
          },
          "docs": "Ingests a change event (deployment, config change) for alert correlation."
        }
      ]
    },
    {
      "info": {
        "name": "Audit",
        "type": "folder"
      },
      "items": [
        {
          "info": {
            "name": "BigPanda Get Audit Logs",
            "type": "http"
          },
          "http": {
            "method": "GET",
            "url": "https://api.bigpanda.io/resources/v2.0/audit/logs",
            "params": [
              {
                "name": "from",
                "value": "",
                "type": "query",
                "description": "Start timestamp for log query."
              },
              {
                "name": "to",
                "value": "",
                "type": "query",
                "description": "End timestamp for log query."
              }
            ],
            "auth": {
              "type": "bearer",
              "token": "{{bearerToken}}"
            }
          },
          "docs": "Returns audit log entries for API and user activity."
        }
      ]
    }
  ],
  "bundled": true
}